setup.py
simple_read_mutator/__init__.py
simple_read_mutator/mutator.py
simple_read_mutator.egg-info/PKG-INFO
simple_read_mutator.egg-info/SOURCES.txt
simple_read_mutator.egg-info/dependency_links.txt
simple_read_mutator.egg-info/not-zip-safe
simple_read_mutator.egg-info/requires.txt
simple_read_mutator.egg-info/top_level.txt