Metadata-Version: 1.1
Name: simple-read-mutator
Version: 0.0.2
Summary: Simple Read Mutator
Home-page: http://github.com/ivargr/simple_read_mutator
Author: Ivar Grytten
Author-email: UNKNOWN
License: MIT
Platform: UNKNOWN
Classifier: Programming Language :: Python :: 3
